lil_buff_writer/__init__.py
lil_buff_writer/__main__.py
lil_buff_writer-0.1.1.dist-info/LICENSE
lil_buff_writer-0.1.1.dist-info/METADATA
lil_buff_writer-0.1.1.dist-info/WHEEL
lil_buff_writer-0.1.1.dist-info/top_level.txt
lil_buff_writer-0.1.1.dist-info/RECORD
