Metadata-Version: 2.2
Name: lil_buff_writer
Version: 0.1.1
Summary: Buffer writing utility package
Author-email: Matthew Taylor <matthew.taylor.andre@gmail.com>
License: Apache-2.0
Project-URL: Homepage, https://github.com/MatthewAndreTaylor/lil_buff_writer
Keywords: writing,buffer,utility
Classifier: Development Status :: 5 - Production/Stable
Classifier: License :: OSI Approved :: Apache Software License
Classifier: Programming Language :: Python :: 3.9
Classifier: Programming Language :: Python :: 3.10
Classifier: Programming Language :: Python :: 3.11
Classifier: Programming Language :: Python :: 3.12
Classifier: Programming Language :: Python :: 3.13
Classifier: Framework :: AsyncIO
Requires-Python: >=3.9
License-File: LICENSE
Requires-Dist: aiofiles
Provides-Extra: dev
Requires-Dist: pytest; extra == "dev"
Requires-Dist: pytest-asyncio; extra == "dev"
Requires-Dist: black; extra == "dev"
